printer/__init__.py
printer_py-0.0.14.dist-info/METADATA
printer_py-0.0.14.dist-info/WHEEL
printer_py-0.0.14.dist-info/top_level.txt
printer_py-0.0.14.dist-info/RECORD
