Metadata-Version: 2.1
Name: printer-py
Version: 0.0.14
Summary: A printer package helps you to debug using print any number of variables of any types only with comma or other operators you want.
Home-page: UNKNOWN
Author: Ninad Goswamy (ninsgosai)
Author-email: <ninad.goswamy@gmail.com>
License: UNKNOWN
Keywords: python,debug,print,diffrent type value,python debug,python2,printer_py,printer-py
Platform: UNKNOWN
Classifier: Development Status :: 1 - Planning
Classifier: Intended Audience :: Developers
Classifier: Programming Language :: Python :: 2
Classifier: Programming Language :: Python :: 3
Classifier: Operating System :: Unix
Classifier: Operating System :: MacOS :: MacOS X
Classifier: Operating System :: Microsoft :: Windows
